[
    {
        "name": "pizza",
        "description": "Yummy, pizza!",
        "usedMessage": "🍕 | You ate delicious pizza!",
        "ids": [
            "pz"
        ],
        "sale": true,
        "price": 10,
        "usable": true
    },
    {
        "name": "banknote",
        "description": "A banknote. Used to expand your bank storage.",
        "ids": [
            "bn"
        ],
        "sale": false,
        "price": 0,
        "usable": true
    },
    {
        "name": "topmedal",
        "description": "Why would you even buy this.",
        "ids": [
            "medal"
        ],
        "sale": true,
        "price": 10000000,
        "usable": false
    }
]